[ 
    {
        "date": "Jan 26, 2022",
        "term": "W22",
        "topics": [
            "The Definite Integral"
        ],
        "notes": "https://utoronto-my.sharepoint.com/:b:/g/personal/jtony_cao_mail_utoronto_ca/EeqO0YqhzL1DpFA8U7rIPRoBVvJmdulQCA9HDElQJN6uZg?e=wqz0uo"
    },
    {
        "date": "Jan 18, 2022",
        "term": "W22",
        "topics": [
            "Intro/Admin", 
            "Sigma Notation",
            "Rienmann Sums"
        ],
        "notes": "https://utoronto-my.sharepoint.com/:b:/g/personal/jtony_cao_mail_utoronto_ca/Edh_-bB0RLpPrELkuZUlmJoBCw1J7pnmAjUyPpBG9S7Caw?e=gFUUNG"
    }
]